geoinsight/__init__.py
geoinsight/api.py
geoinsight/util.py
geoinsight-0.8.1.dist-info/METADATA
geoinsight-0.8.1.dist-info/WHEEL
geoinsight-0.8.1.dist-info/licenses/LICENSE
geoinsight-0.8.1.dist-info/RECORD
