Metadata-Version: 2.3
Name: geoinsight
Version: 0.8.1
Summary: GeoInsight Python Package
Author-email: GeoInsight <info@geoinsight.ai>
License-File: LICENSE
Classifier: License :: OSI Approved :: MIT License
Classifier: Operating System :: OS Independent
Classifier: Programming Language :: Python :: 3
Requires-Python: >=3.6
Requires-Dist: auth0-python>=4.4.2
Requires-Dist: geopandas>=0.14.0
Requires-Dist: pandas>=2.1.1
Requires-Dist: requests>=2.31.0
Requires-Dist: shapely>=2.0.1
